{
  "jobId": "2cb00c69-1af2-4c75-832f-11e6b82cb926",
  "clientCode": "01",
  "selectedDomain": "www.meeraind.com",
  "keywords": [
    "Cone To Cone Winder",
    "Textile Twister",
    "heat setting machine price",
    "tfo machine",
    "Cone Winder",
    "TFO",
    "pp fibrillated yarn",
    "Doubling Machines",
    "yarn twisting and doubling machine",
    "Assembly winder",
    "jari covering machine surat",
    "Heavy Ring Twister",
    "heat setting machine",
    "Rope Twister",
    "textile doubling machine",
    "Lycra Covering Machine",
    "Two For One Twisting Machine",
    "TFO Twisting Machine",
    "covering machine",
    "Bobbin Winder"
  ],
  "status": "COMPLETED",
  "stage": "DONE",
  "progress": {
    "IN": {
      "done": 0,
      "total": 20,
      "current": "Chunk 1 completed"
    },
    "GL": {
      "done": 0,
      "total": 20,
      "current": "Chunk 1 completed"
    }
  },
  "errors": [],
  "startedAt": "2025-12-26T15:30:21.395Z",
  "updatedAt": "2025-12-26T15:39:13.977Z",
  "completedAt": "2025-12-26T15:39:13.977Z"
}